yandex_aiobot_py/__init__.py
yandex_aiobot_py/apihelpers.py
yandex_aiobot_py/bot_types.py
yandex_aiobot_py/client.py
yandex_aiobot_py/handlers.py
yandex_aiobot_py-0.2.1.dist-info/licenses/LICENSE
yandex_aiobot_py-0.2.1.dist-info/METADATA
yandex_aiobot_py-0.2.1.dist-info/WHEEL
yandex_aiobot_py-0.2.1.dist-info/top_level.txt
yandex_aiobot_py-0.2.1.dist-info/RECORD
