Metadata-Version: 2.4
Name: yandex-aiobot-py
Version: 0.2.1
Summary: Асинхронная библиотека для создания ботов в Яндекс Мессенджере
Home-page: https://github.com/your/repo
Author: demkinkv
Author-email: demkinkv <demkinkv92@yandex.com>
License: MIT
Project-URL: Homepage, https://gitlab.com/demkinkv/yandex_aiobot_py
Project-URL: Repository, https://gitlab.com/demkinkv/yandex_aiobot_py.git
Project-URL: Documentation, https://gitlab.com/demkinkv/yandex_aiobot_py/-/blob/main/README.md
Project-URL: Issues, https://gitlab.com/demkinkv/yandex_aiobot_py/-/issues
Keywords: yandex,messenger,chat,bot,asyncio,api,yandex-chat
Classifier: Development Status :: 5 - Production/Stable
Classifier: Intended Audience :: Developers
Classifier: Topic :: Communications :: Chat
Classifier: Topic :: Software Development :: Libraries :: Python Modules
Classifier: License :: OSI Approved :: MIT License
Classifier: Programming Language :: Python :: 3
Classifier: Programming Language :: Python :: 3.9
Classifier: Programming Language :: Python :: 3.10
Classifier: Programming Language :: Python :: 3.11
Classifier: Programming Language :: Python :: 3.12
Classifier: Programming Language :: Python :: 3.13
Classifier: Framework :: AsyncIO
Classifier: Operating System :: OS Independent
Requires-Python: >=3.8
License-File: LICENSE
Requires-Dist: aiohttp>=3.9.0
Requires-Dist: aiofiles>=23.2.0
Provides-Extra: dev
Requires-Dist: pytest>=7.0; extra == "dev"
Requires-Dist: pytest-asyncio; extra == "dev"
Requires-Dist: aioresponses; extra == "dev"
Requires-Dist: black; extra == "dev"
Requires-Dist: isort; extra == "dev"
Requires-Dist: mypy; extra == "dev"
Dynamic: author
Dynamic: home-page
Dynamic: license-file
Dynamic: requires-python
